odoo10_addon_mrp_production_service-10.0.1.0.1-py2.7-nspkg.pth
odoo/addons/mrp_production_service/README.rst
odoo/addons/mrp_production_service/__init__.py
odoo/addons/mrp_production_service/__manifest__.py
odoo/addons/mrp_production_service/i18n/mrp_production_service.pot
odoo/addons/mrp_production_service/models/__init__.py
odoo/addons/mrp_production_service/models/mrp_production.py
odoo/addons/mrp_production_service/static/description/icon.png
odoo/addons/mrp_production_service/tests/__init__.py
odoo/addons/mrp_production_service/tests/test_mrp_production_service.py
odoo10_addon_mrp_production_service-10.0.1.0.1.dist-info/METADATA
odoo10_addon_mrp_production_service-10.0.1.0.1.dist-info/RECORD
odoo10_addon_mrp_production_service-10.0.1.0.1.dist-info/WHEEL
odoo10_addon_mrp_production_service-10.0.1.0.1.dist-info/namespace_packages.txt
odoo10_addon_mrp_production_service-10.0.1.0.1.dist-info/top_level.txt
