Metadata-Version: 2.1
Name: odoo10-addon-mrp-production-service
Version: 10.0.1.0.1
Summary: Creates procurement orders from manufacturing orders, for services included in the Bill of Materials
Home-page: https://www.odoo-community.org
Author: Eficent,Odoo Community Association (OCA)
Author-email: support@odoo-community.org
License: AGPL-3
Platform: UNKNOWN
Classifier: Programming Language :: Python
Classifier: Framework :: Odoo
Classifier: License :: OSI Approved :: GNU Affero General Public License v3
Requires-Python: ~=2.7
Requires-Dist: odoo (<10.1dev,>=10.0)
